setup.cfg
setup.py
aliyun_python_sdk_emr_hack.egg-info/PKG-INFO
aliyun_python_sdk_emr_hack.egg-info/SOURCES.txt
aliyun_python_sdk_emr_hack.egg-info/dependency_links.txt
aliyun_python_sdk_emr_hack.egg-info/pbr.json
aliyun_python_sdk_emr_hack.egg-info/requires.txt
aliyun_python_sdk_emr_hack.egg-info/top_level.txt
aliyunsdkemr/__init__.py
aliyunsdkemr/request/__init__.py
aliyunsdkemr/request/v20160408/CreateClusterRequest.py
aliyunsdkemr/request/v20160408/CreateExecutionPlanRequest.py
aliyunsdkemr/request/v20160408/CreateJobRequest.py
aliyunsdkemr/request/v20160408/DeleteExecutionPlanRequest.py
aliyunsdkemr/request/v20160408/DeleteJobRequest.py
aliyunsdkemr/request/v20160408/DescribeClusterRequest.py
aliyunsdkemr/request/v20160408/DescribeExecutionPlanRequest.py
aliyunsdkemr/request/v20160408/DescribeJobRequest.py
aliyunsdkemr/request/v20160408/GetClusterStatusRequest.py
aliyunsdkemr/request/v20160408/KillExecutionJobInstanceRequest.py
aliyunsdkemr/request/v20160408/KillExecutionPlanInstanceRequest.py
aliyunsdkemr/request/v20160408/ListAvailableConfigRequest.py
aliyunsdkemr/request/v20160408/ListClustersRequest.py
aliyunsdkemr/request/v20160408/ListExecutionPlanInstancesRequest.py
aliyunsdkemr/request/v20160408/ListExecutionPlansRequest.py
aliyunsdkemr/request/v20160408/ListJobExecutionInstancesRequest.py
aliyunsdkemr/request/v20160408/ListJobInstanceWorkersRequest.py
aliyunsdkemr/request/v20160408/ListJobsRequest.py
aliyunsdkemr/request/v20160408/ModifyClusterNameRequest.py
aliyunsdkemr/request/v20160408/ModifyExecutionPlanRequest.py
aliyunsdkemr/request/v20160408/ModifyJobRequest.py
aliyunsdkemr/request/v20160408/QueryPriceRequest.py
aliyunsdkemr/request/v20160408/ReleaseClusterRequest.py
aliyunsdkemr/request/v20160408/RenewClusterRequest.py
aliyunsdkemr/request/v20160408/ResizeClusterRequest.py
aliyunsdkemr/request/v20160408/ResumeExecutionPlanSchedulerRequest.py
aliyunsdkemr/request/v20160408/RunExecutionPlanRequest.py
aliyunsdkemr/request/v20160408/SuspendExecutionPlanSchedulerRequest.py
aliyunsdkemr/request/v20160408/__init__.py