Metadata-Version: 1.1
Name: aliyun-python-sdk-emr-hack
Version: 0.1.2
Summary: A pip package
Home-page: UNKNOWN
Author: Liwen
Author-email: UNKNOWN
License: MIT
Platform: UNKNOWN
Classifier: Programming Language :: Python
Classifier: Programming Language :: Python :: 3.5
